{
  "losetas": [
    {
      "nombre": "R17",
      "imagen": "images/losetas/R17.png",
      "matriz": [
        [1, 1, 1, 1, 1, 1],
        [1, 1, 1, 1, 1, 1],
        [1, 1, 1, 1, 1, 1],
        [1, 1, 1, 1, 1, 1],
        [1, 1, 1, 1, 1, 1],
        [1, 1, 1, 1, 1, 1]
      ]
    },
    {
      "nombre": "R11",
      "imagen": "images/losetas/R11.png",
      "matriz": [
        [0, 0, 1, 1, 1, 1],
        [0, 0, 1, 1, 1, 1],
        [1, 1, 1, 1, 1, 1],
        [1, 1, 1, 1, 1, 1],
        [1, 1, 1, 1, 1, 1],
        [1, 1, 1, 1, 1, 1]
      ]
    },
    {
      "nombre": "R10",
      "imagen": "images/losetas/R10.png",
      "matriz": [
        [0, 0, 1, 1, 1, 1],
        [0, 0, 1, 1, 1, 0],
        [1, 1, 1, 1, 1, 0],
        [1, 1, 1, 1, 1, 0],
        [0, 0, 1, 1, 1, 0],
        [0, 0, 1, 1, 1, 1]
      ]
    },
    {
      "nombre": "R9",
      "imagen": "images/losetas/R9.png",
      "matriz": [
        [0, 0, 1, 1, 1, 1],
        [0, 0, 1, 1, 1, 1],
        [1, 1, 1, 0, 0, 1],
        [1, 1, 1, 0, 0, 1],
        [0, 0, 1, 1, 1, 1],
        [0, 0, 1, 1, 1, 1]
      ]
    },{
      "nombre": "R7B",
      "imagen": "images/losetas/R7B.png",
      "matriz": [
        [1, 1, 1, 1, 1, 1],
        [1, 1, 1, 1, 1, 1],
        [1, 1, 1, 1, 1, 1],
        [1, 1, 1, 1, 1, 1],
        [1, 1, 1, 1, 1, 1],
        [1, 1, 1, 1, 1, 1]
      ]
    },
    {
      "nombre": "R7",
      "imagen": "images/losetas/R7.png",
      "matriz": [
        [1, 1, 1, 1, 0, 0],
        [1, 1, 1, 1, 1, 0],
        [1, 1, 1, 1, 1, 1],
        [1, 1, 1, 1, 1, 1],
        [1, 1, 1, 1, 1, 0],
        [0, 0, 1, 1, 1, 0]
      ]
    },
    {
      "nombre": "R6B",
      "imagen": "images/losetas/R6B.png",
      "matriz": [
        [1, 1, 1, 1, 1, 1],
        [1, 1, 1, 1, 1, 1],
        [1, 1, 1, 1, 1, 1],
        [1, 1, 1, 1, 1, 1],
        [1, 1, 1, 1, 1, 1],
        [1, 1, 1, 1, 1, 1]
      ]
    },
    {
      "nombre": "R6",
      "imagen": "images/losetas/R6.png",
      "matriz": [
        [1, 0, 0, 0, 0, 1],
        [1, 1, 1, 1, 1, 1],
        [1, 1, 1, 1, 1, 1],
        [1, 1, 1, 1, 1, 1],
        [1, 1, 1, 1, 1, 1],
        [1, 1, 0, 0, 1, 1]
      ]
    },
    {
      "nombre": "R4B",
      "imagen": "images/losetas/R4B.png",
      "matriz": [
        [1, 1, 0, 0, 1, 1],
        [1, 1, 1, 1, 1, 1],
        [1, 1, 1, 1, 1, 1],
        [1, 1, 1, 1, 1, 1],
        [1, 1, 1, 1, 1, 1],
        [1, 1, 1, 1, 1, 1]
      ]
    },
    {
      "nombre": "R4",
      "imagen": "images/losetas/R4.png",
      "matriz": [
        [1, 1, 1, 1, 1, 1],
        [1, 1, 1, 1, 1, 1],
        [1, 1, 1, 1, 1, 1],
        [1, 1, 1, 1, 1, 1],
        [1, 1, 1, 1, 1, 1],
        [1, 1, 1, 1, 1, 1]
      ]
    },
    {
      "nombre": "R3B",
      "imagen": "images/losetas/R3B.png",
      "matriz": [
        [1, 1, 1, 0, 0, 1],
        [1, 1, 1, 1, 1, 1],
        [1, 1, 1, 1, 1, 1],
        [1, 1, 1, 1, 1, 1],
        [1, 1, 1, 1, 1, 1],
        [1, 1, 1, 1, 1, 1]
      ]
    },
    {
      "nombre": "R3",
      "imagen": "images/losetas/R3.png",
      "matriz": [
        [1, 0, 1, 1, 1, 0],
        [1, 1, 1, 1, 1, 1],
        [1, 1, 1, 1, 1, 1],
        [1, 1, 1, 1, 1, 1],
        [1, 1, 1, 1, 1, 1],
        [1, 1, 1, 1, 1, 1]
      ]
    },
    {
      "nombre": "R2B",
      "imagen": "images/losetas/R2B.png",
      "matriz": [
        [1, 1, 1, 1, 1, 1],
        [1, 1, 1, 1, 1, 1],
        [1, 1, 0, 0, 1, 1],
        [1, 1, 0, 0, 1, 1],
        [1, 1, 1, 1, 1, 1],
        [1, 1, 1, 1, 1, 1]
      ]
    },
    {
      "nombre": "R2",
      "imagen": "images/losetas/R2.png",
      "matriz": [
        [1, 1, 1, 1, 1, 1],
        [1, 1, 1, 1, 1, 1],
        [1, 1, 1, 1, 1, 1],
        [1, 1, 1, 1, 1, 1],
        [1, 1, 1, 1, 1, 1],
        [1, 1, 1, 1, 1, 1]
      ]
    },
    {
      "nombre": "R1B",
      "imagen": "images/losetas/R1B.png",
      "matriz": [
        [1, 1, 1, 1, 1, 1],
        [1, 1, 1, 1, 1, 1],
        [1, 1, 1, 1, 1, 1],
        [1, 1, 1, 1, 1, 1],
        [1, 1, 1, 1, 1, 1],
        [1, 1, 1, 1, 1, 1]
      ]
    },
    {
      "nombre": "R1",
      "imagen": "images/losetas/R1.png",
      "matriz": [
        [0, 0, 1, 1, 0, 0],
        [0, 0, 1, 1, 0, 0],
        [0, 0, 1, 1, 0, 0],
        [0, 0, 1, 1, 0, 0],
        [0, 0, 1, 1, 0, 0],
        [0, 0, 1, 1, 0, 0]
      ]
    },
    {
      "nombre": "C10",
      "imagen": "images/losetas/C10.png",
      "matriz": [
        [0, 0, 1, 1, 0, 0],
        [0, 0, 1, 1, 0, 0],
        [1, 1, 1, 1, 1, 1],
        [1, 1, 1, 1, 1, 1],
        [0, 0, 1, 1, 0, 0],
        [0, 0, 1, 1, 0, 0]
      ]
    },
    {
      "nombre": "SALA_DEL_TRONO",
      "imagen": "images/losetas/SALA_DEL_TRONO.png",
      "matriz": [
        [0, 1, 0, 0, 0, 0, 0, 0, 0, 0, 1, 0],
        [1, 1, 0, 0, 0, 0, 0, 0, 0, 0, 1, 1],
        [1, 1, 1, 1, 1, 1, 1, 1, 1, 1, 1, 1],
        [0, 1, 1, 1, 1, 1, 1, 1, 1, 1, 1, 0],
        [1, 1, 1, 1, 1, 1, 1, 1, 1, 1, 1, 1],
        [0, 1, 1, 1, 1, 1, 1, 1, 1, 1, 1, 0]
      ]
    },
    {
      "nombre": "SACRIFICIOS",
      "imagen": "images/losetas/SACRIFICIOS.png",
      "matriz": [
        [1, 0, 1, 1, 1, 0, 0, 1, 1, 1, 1, 1],
        [0, 0, 0, 1, 1, 1, 1, 1, 1, 1, 1, 1],
        [0, 0, 0, 1, 1, 0, 0, 1, 1, 1, 1, 1],
        [0, 0, 0, 1, 1, 0, 0, 1, 1, 1, 1, 1],
        [0, 0, 0, 1, 1, 1, 1, 1, 1, 1, 1, 1],
        [1, 0, 1, 1, 1, 1, 1, 1, 1, 1, 1, 1]
      ]
    },
    {
      "nombre": "RIO_DE_LAVA",
      "imagen": "images/losetas/RIO_DE_LAVA.png",
      "matriz": [
        [0, 1, 0, 1, 1, 0, 0, 1, 1, 1, 1, 1],
        [1, 1, 1, 1, 1, 0, 0, 1, 1, 0, 1, 1],
        [0, 1, 1, 1, 1, 1, 1, 1, 1, 1, 1, 1],
        [0, 1, 1, 1, 1, 1, 1, 1, 1, 1, 1, 1],
        [1, 1, 1, 1, 1, 0, 0, 1, 1, 0, 1, 1],
        [0, 1, 0, 1, 1, 0, 0, 1, 1, 1, 1, 1]
      ]
    },
    {
      "nombre": "R18",
      "imagen": "images/losetas/R18.png",
      "matriz": [
        [0, 0, 1, 1, 1, 1, 1, 1, 1, 1, 1, 1],
        [0, 1, 1, 1, 1, 1, 1, 1, 1, 1, 1, 1],
        [1, 1, 1, 1, 1, 1, 1, 1, 1, 1, 1, 1],
        [1, 1, 1, 1, 1, 1, 1, 1, 1, 1, 1, 1],
        [1, 1, 1, 1, 1, 1, 1, 1, 1, 1, 1, 1],
        [1, 1, 1, 1, 1, 1, 0, 1, 0, 1, 1, 1]
      ]
    },
    {
      "nombre": "R5B",
      "imagen": "images/losetas/R5B.png",
      "matriz": [
        [1, 1, 0, 1, 1, 1, 1, 1, 1, 1, 1, 1],
        [1, 1, 1, 1, 1, 1, 1, 1, 1, 1, 1, 1],
        [1, 1, 1, 1, 1, 1, 1, 1, 1, 1, 1, 1],
        [1, 1, 1, 1, 1, 1, 1, 1, 1, 1, 1, 1],
        [1, 1, 1, 1, 1, 1, 1, 1, 1, 1, 1, 1],
        [1, 1, 0, 1, 1, 1, 1, 1, 1, 1, 1, 1]
      ]
    },
    {
      "nombre": "R5",
      "imagen": "images/losetas/R5.png",
      "matriz": [
        [1, 1, 0, 1, 1, 1, 1, 1, 0, 0, 1, 1],
        [1, 0, 1, 1, 0, 1, 1, 0, 1, 1, 0, 1],
        [1, 1, 1, 1, 1, 1, 1, 1, 1, 1, 1, 1],
        [1, 1, 1, 1, 1, 1, 1, 1, 1, 1, 1, 1],
        [1, 0, 1, 1, 0, 1, 1, 0, 1, 1, 0, 1],
        [1, 1, 0, 0, 1, 1, 1, 1, 0, 0, 1, 1]
      ]
    },
    {
      "nombre": "LA_GRAN_CRIPTA",
      "imagen": "images/losetas/LA_GRAN_CRIPTA.png",
      "matriz": [
        [1, 1, 1, 1, 1, 1, 1, 1, 1, 1, 1, 1],
        [1, 1, 1, 1, 1, 1, 1, 1, 1, 1, 1, 1],
        [1, 1, 1, 1, 1, 1, 1, 1, 1, 1, 1, 1],
        [1, 1, 1, 1, 1, 1, 1, 1, 1, 1, 1, 1],
        [1, 1, 1, 1, 1, 1, 1, 1, 1, 1, 1, 1],
        [1, 1, 1, 1, 1, 1, 1, 1, 1, 1, 1, 1]
      ]
    },
    {
      "nombre": "R15",
      "imagen": "images/losetas/R15.png",
      "matriz": [
        [1, 0, 1, 0],
        [1, 1, 1, 0],
        [1, 1, 1, 1],
        [1, 1, 1, 0]
      ]
    },
    {
      "nombre": "R14",
      "imagen": "images/losetas/R14.png",
      "matriz": [
        [1, 1, 1, 1],
        [1, 0, 0, 1],
        [1, 0, 0, 1],
        [1, 1, 1, 1]
      ]
    },
    {
      "nombre": "R13",
      "imagen": "images/losetas/R13.png",
      "matriz": [
        [1, 1, 1, 1],
        [1, 1, 1, 1],
        [1, 1, 1, 1],
        [1, 1, 1, 1]
      ]
    },
    {
      "nombre": "R12",
      "imagen": "images/losetas/R12.png",
      "matriz": [
        [1, 0, 0, 1],
        [1, 1, 1, 1],
        [1, 1, 1, 1],
        [1, 0, 0, 1]
      ]
    },
    {
      "nombre": "R8B",
      "imagen": "images/losetas/R8B.png",
      "matriz": [
        [1, 1, 1, 1],
        [1, 1, 1, 1],
        [1, 1, 1, 1],
        [1, 1, 1, 1]
      ]
    },
    {
      "nombre": "R8",
      "imagen": "images/losetas/R8.png",
      "matriz": [
        [1, 1, 1, 1],
        [1, 1, 1, 1],
        [1, 1, 1, 1],
        [1, 1, 1, 1]
      ]
    },
    {
      "nombre": "C14",
      "imagen": "images/losetas/C14.png",
      "matriz": [
        [1, 1, 1, 1],
        [1, 1, 1, 1],
        [0, 0, 1, 1],
        [0, 0, 1, 1]
      ]
    },
    {
      "nombre": "C13",
      "imagen": "images/losetas/C13.png",
      "matriz": [
        [1, 1, 1, 1],
        [1, 1, 1, 1],
        [0, 0, 1, 1],
        [0, 0, 1, 1]
      ]
    },
    {
      "nombre": "C12",
      "imagen": "images/losetas/C12.png",
      "matriz": [
        [1, 1, 1, 1],
        [1, 1, 1, 1],
        [0, 0, 1, 1],
        [0, 0, 1, 1]
      ]
    },
    {
      "nombre": "R16",
      "imagen": "images/losetas/R16.png",
      "matriz": [
        [1, 1, 0, 0],
        [1, 1, 1, 0],
        [1, 1, 1, 0],
        [1, 1, 1, 1],
        [1, 1, 1, 1],
        [1, 1, 0, 0]
      ]
    },
    {
      "nombre": "C11",
      "imagen": "images/losetas/C11.png",
      "matriz": [
        [1, 1, 1, 1, 1, 1],
        [1, 1, 1, 1, 1, 1],
        [0, 0, 1, 1, 0, 0],
        [0, 0, 1, 1, 0, 0]
      ]
    },
    {
      "nombre": "C18",
      "imagen": "images/losetas/C18.png",
      "matriz": [
        [1, 1, 1, 1, 1, 1],
        [1, 1, 1, 1, 1, 1]
      ]
    },
    {
      "nombre": "C17",
      "imagen": "images/losetas/C17.png",
      "matriz": [
        [1, 1, 1, 1, 1, 1],
        [1, 1, 1, 1, 1, 1]
      ]
    },
    {
      "nombre": "C9",
      "imagen": "images/losetas/C9.png",
      "matriz": [
        [1, 1, 0, 0, 1, 1],
        [1, 1, 0, 0, 1, 1]
      ]
    },
    {
      "nombre": "C8",
      "imagen": "images/losetas/C8.png",
      "matriz": [
        [1, 1, 1, 1, 1, 1],
        [1, 1, 1, 1, 1, 1]
      ]
    },
    {
      "nombre": "C7",
      "imagen": "images/losetas/C7.png",
      "matriz": [
        [1, 1, 1, 1, 1, 1],
        [1, 1, 1, 1, 1, 1]
      ]
    },
    {
      "nombre": "C6",
      "imagen": "images/losetas/C6.png",
      "matriz": [
        [1, 1, 1, 1, 1, 1],
        [1, 1, 1, 1, 1, 1]
      ]
    },
    {
      "nombre": "C5",
      "imagen": "images/losetas/2x6.png",
      "matriz": [
        [1, 1, 0, 1, 1, 1],
        [1, 1, 1, 1, 1, 1]
      ]
    },
    {
      "nombre": "C4",
      "imagen": "images/losetas/C4.png",
      "matriz": [
        [1, 1, 1, 1, 1, 1],
        [1, 1, 1, 1, 1, 1]
      ]
    },
    {
      "nombre": "C3",
      "imagen": "images/losetas/C3.png",
      "matriz": [
        [1, 1, 1, 1, 1, 1],
        [1, 1, 1, 1, 1, 1]
      ]
    },
    {
      "nombre": "C2",
      "imagen": "images/losetas/C2.png",
      "matriz": [
        [1, 1, 1, 1, 1, 1],
        [1, 1, 1, 1, 1, 1]
      ]
    },
    {
      "nombre": "C1",
      "imagen": "images/losetas/C1.png",
      "matriz": [
        [1, 1, 1, 1, 1, 1],
        [1, 1, 1, 1, 1, 1]
      ]
    },
    {
      "nombre": "ENTRADA",
      "imagen": "images/losetas/ENTRADA.png",
      "matriz": [
        [1, 1, 1, 1],
        [1, 1, 1, 1]
      ]
    },
    {
      "nombre": "C16",
      "imagen": "images/losetas/C16.png",
      "matriz": [
        [1, 1, 1, 1],
        [1, 1, 1, 1]
      ]
    },
    {
      "nombre": "C15",
      "imagen": "images/losetas/C15.png",
      "matriz": [
        [0, 0, 1, 1],
        [0, 0, 1, 1]
      ]
    },
    {
      "nombre": "GUARIDA_DE_LADRONES",
      "imagen": "images/losetas/GUARIDA_DE_LADRONES.png",
      "matriz": [
        [0, 0, 0, 0, 0, 0, 0, 0, 0, 0, 0, 0],
        [0, 0, 0, 1, 1, 0, 0, 1, 1, 0, 0, 0],
        [0, 0, 1, 1, 1, 1, 1, 1, 1, 1, 0, 0],
        [0, 1, 0, 1, 1, 1, 1, 1, 1, 0, 1, 0],
        [1, 1, 0, 1, 1, 1, 1, 1, 1, 0, 1, 1],
        [0, 1, 1, 0, 1, 1, 1, 1, 0, 1, 1, 0],
        [1, 1, 1, 1, 0, 1, 1, 0, 1, 1, 1, 1],
        [1, 1, 1, 1, 1, 1, 1, 1, 1, 1, 1, 1],
        [1, 1, 1, 1, 1, 1, 1, 1, 1, 1, 1, 1],
        [1, 0, 1, 1, 1, 1, 1, 1, 0, 0, 1, 1],
        [1, 1, 0, 1, 0, 1, 1, 0, 0, 0, 1, 1]
      ]
    }
  ]
}